Workbook
Name Slicer_Salesperson: #N/A

Sheet PVT_Top5_Salespersons
A3: Sales Person | B3: Net___Sales
A4: Sneha | B4: 7349314.8
A5: Meena | B5: 6498767.8
A6: Rahul | B6: 6165693.7
A7: Priya | B7: 5996814.5
A8: Vikram | B8: 5721954.6
A9: Grand Total | B9: 31732546

Sheet Top 5 Districts by Net Sales
A3: District Perfomance | B3: Net Sales
A4: Coimbatore | B4: 12067506
A5: Madurai | B5: 11874875
A6: Tiruchirappalli | B6: 11581372
A7: Chennai | B7: 10829805
A8: Grand Total | B8: 46353559

Sheet Sheet2
A1: SALES PERFORMANCE DASHBOARD
A2: Sales Perfomance Analysis | Quarterly . District . Product . Salesperson
A4: TOTAL NET SALES | D4: TOTAL ORDERS | G4: TOP SALESPERSON | J4: TOP PRODUCT | M4: AVERAGE ORDER VALUE
A5: =SUM(Sales_Data!Q:Q) -> 46353559 | D5: =COUNTA(Sales_Data!A:A)-1 -> 421 | G5: =INDEX(PVT_Top5_Salespersons!A4:A8,MATCH(MAX(PVT_Top5_Salespersons!B4:B8),PVT_Top5_Salespersons!B4:B8,0)) -> Sneha | J5: =INDEX('Top 5 Products by Sum of Netsal'!A2:A6,MATCH(MAX('Top 5 Products by Sum of Netsal'!B2:B6),'Top 5 Products by Sum of Netsal'!B2:B6,0)) -> French Doors | M5: =46353558.9/421 -> 110103.47

Sheet Top 5 Products by Sum of Netsal
A3: Product | B3: Net Sales
A4: French Doors | B4: 9280504.8
A5: Bi-Fold Doors | B5: 8533032
A6: Sliding Doors | B6: 6363407.2
A7: Soundproof Windows | B7: 5258497.4
A8: Casement Windows | B8: 4570298.5
A9: Grand Total | B9: 34005740

Sheet PVT_Monthly_Performance
A1: Salesperson | B1: Vikram
A3: Months | B3: Net Sales
A4: January | B4: 0
A5: February | B5: 876319.2
A6: March | B6: 855786.7
A7: April | B7: 238214.2
A8: May | B8: 802665.8
A9: June | B9: 471945.55
A10: July | B10: 414507.6
A11: August | B11: 853973.6
A12: September | B12: 413624.4
A13: October | B13: 160012.8
A14: November | B14: 172484.6
A15: December | B15: 462420.2
A16: Grand Total | B16: 5721954.7

Sheet PVT_Quarterly_Performance
A1: Salesperson | B1: Vikram
D2: D | E2: E | F2: F
A3: Quarters | B3: Net__Sales | D3: Quarter | E3: Selected Salesperson | F3: Average Benchmark
A4: Q1 | B4: 1732105.9 | D4: Q1 | E4: =B4 -> 1732105.9 | F4: 1399592.3
A5: Q2 | B5: 1512825.6 | D5: Q2 | E5: =B5 -> 1512825.6 | F5: 1646009.7
A6: Q3 | B6: 1682105.6 | D6: Q3 | E6: =B6 -> 1682105.6 | F6: 1381220.7
A7: Q4 | B7: 794917.6 | D7: Q4 | E7: =B7 -> 794917.6 | F7: 1367372.2
A8: Grand Total | B8: 5721954.7

Sheet PVT_Performance_Benchmark
A3: Sum of Net_Sales | B3: Column Labels
A4: Row Labels | B4: Arun | C4: Divya | D4: Karthik | E4: Meena | F4: Priya | G4: Rahul | H4: Sneha | I4: Vikram | J4: Grand Total | K4: Average Benchmark | M4: Quarter | N4: Performance vs Average
A5: Q1 | B5: 1575754.2 | C5: 138369.2 | D5: 1261737 | E5: 1277045.7 | F5: 1774255.2 | G5: 1685300.8 | H5: 1752170.2 | I5: 1732105.9 | J5: 11196738 | K5: =J5/8 -> 1399592.3 | M5: Q1 | N5: =H5/K5-1 -> 0.25191471
A6: Q2 | B6: 1563568.5 | C6: 1080488.9 | D6: 1630960.1 | E6: 2319745.7 | F6: 1100872.9 | G6: 2037272.3 | H6: 1922343.6 | I6: 1512825.6 | J6: 13168078 | K6: =J6/8 -> 1646009.7 | M6: Q2 | N6: =H6/K6-1 -> 0.16788109
A7: Q3 | B7: 1344733.3 | C7: 1008400.5 | D7: 1036106.5 | E7: 1598468.3 | F7: 1459635.4 | G7: 1061080.4 | H7: 1859235.8 | I7: 1682105.6 | J7: 11049766 | K7: =J7/8 -> 1381220.7 | M7: Q3 | N7: =H7/K7-1 -> 0.34608163
A8: Q4 | B8: 1197625.2 | C8: 1568962.6 | D8: 1214307.4 | E8: 1303508.2 | F8: 1662050.9 | G8: 1382040.2 | H8: 1815565.2 | I8: 794917.6 | J8: 10938977 | K8: =J8/8 -> 1367372.2 | M8: Q4 | N8: =H8/K8-1 -> 0.32777695

Sheet Sales_Data
A1: Order_ID | B1: Customer_ID | C1: Product | D1: Order_Date | E1: Customer_Type | F1: District | G1: Salesperson | H1: Lead_Source | I1: Product_ID | J1: Product2 | K1: Category | L1: Quantity | M1: Unit_Price | N1: Discount_% | O1: Gross_Value | P1: Discount_Value | Q1: Net_Sales | R1: Year | S1: MONTH | T1: MONTH_NUMBER | U1: QUARTER | V1: Lead_Status | W1: Payment_Status | X1: Installation_Status | Y1: Site_Visit_Days | Z1: Installation_Days | AA1: Customer_Rating | AB1: Month2 | AC1: Quarter2 | AD1: Year2
A2: FN10002 | B2: CUST1002 | C2: =_xlfn.XLOOKUP(Sales_Data[[#This Row],[Product_ID]],Product_Master[Product_ID],Product_Master[Product],"Not Found") -> Soundproof Windows | D2: 45951 | E2: Commercial | F2: Coimbatore | G2: Divya | H2: Walk-in | I2: P008 | J2: Soundproof Windows | K2: Windows | L2: 2 | M2: 45381 | N2: 0.05 | O2: 90762 | P2: 4538.1 | Q2: 86223.9 | R2: =YEAR(Sales_Data[[#This Row],[Order_Date]]) -> 2025 | S2: =TEXT(Sales_Data[[#This Row],[Order_Date]],"mmmm") -> October | T2: =MONTH($D2) -> 10 | U2: ="Q"&ROUNDUP(MONTH(Sales_Data[[#This Row],[Order_Date]])/3,0) -> Q4 | V2: Converted | W2: Paid | X2: In Progress | Y2: 2 | Z2: 20 | AA2: 3 | AB2: Oct | AC2: Q4 | AD2: 2025
A3: FN10003 | B3: CUST1003 | C3: =_xlfn.XLOOKUP(Sales_Data[[#This Row],[Product_ID]],Product_Master[Product_ID],Product_Master[Product],"Not Found") -> Bi-Fold Doors | D3: 45832 | E3: Commercial | F3: Chennai | G3: Rahul | H3: Walk-in | I3: P006 | J3: Bi-Fold Doors | K3: Doors | L3: 6 | M3: 52245 | N3: 0.1 | O3: 313470 | P3: 31347 | Q3: 282123 | R3: =YEAR(Sales_Data[[#This Row],[Order_Date]]) -> 2025 | S3: =TEXT(Sales_Data[[#This Row],[Order_Date]],"mmmm") -> June | T3: =MONTH($D3) -> 6 | U3: ="Q"&ROUNDUP(MONTH(Sales_Data[[#This Row],[Order_Date]])/3,0) -> Q2 | V3: Negotiation | W3: Paid | X3: Completed | Y3: 4 | Z3: 29 | AA3: 5 | AB3: Jun | AC3: Q2 | AD3: 2025
A4: FN10005 | B4: CUST1005 | C4: =_xlfn.XLOOKUP(Sales_Data[[#This Row],[Product_ID]],Product_Master[Product_ID],Product_Master[Product],"Not Found") -> Aluminium Windows | D4: 45711 | E4: Commercial | F4: Coimbatore | G4: Sneha | H4: Google Ads | I4: P002 | J4: Aluminium Windows | K4: Windows | L4: 2 | M4: 22922 | N4: 0 | O4: 45844 | P4: 0 | Q4: 45844 | R4: =YEAR(Sales_Data[[#This Row],[Order_Date]]) -> 2025 | S4: =TEXT(Sales_Data[[#This Row],[Order_Date]],"mmmm") -> February | T4: =MONTH($D4) -> 2 | U4: ="Q"&ROUNDUP(MONTH(Sales_Data[[#This Row],[Order_Date]])/3,0) -> Q1 | V4: Converted | W4: Pending | X4: In Progress | Y4: 7 | Z4: 12 | AA4: 4 | AB4: Feb | AC4: Q1 | AD4: 2025
A5: FN10008 | B5: CUST1008 | C5: =_xlfn.XLOOKUP(Sales_Data[[#This Row],[Product_ID]],Product_Master[Product_ID],Product_Master[Product],"Not Found") -> uPVC Windows | D5: 45985 | E5: Residential | F5: Madurai | G5: Meena | H5: Walk-in | I5: P001 | J5: uPVC Windows | K5: Windows | L5: 4 | M5: 17689 | N5: 0 | O5: 70756 | P5: 0 | Q5: 70756 | R5: =YEAR(Sales_Data[[#This Row],[Order_Date]]) -> 2025 | S5: =TEXT(Sales_Data[[#This Row],[Order_Date]],"mmmm") -> November | T5: =MONTH($D5) -> 11 | U5: ="Q"&ROUNDUP(MONTH(Sales_Data[[#This Row],[Order_Date]])/3,0) -> Q4 | V5: Site Visit | W5: Partially Paid | X5: Scheduled | Y5: 1 | Z5: 7 | AA5: 2 | AB5: Nov | AC5: Q4 | AD5: 2025
A6: FN10009 | B6: CUST1009 | C6: =_xlfn.XLOOKUP(Sales_Data[[#This Row],[Product_ID]],Product_Master[Product_ID],Product_Master[Product],"Not Found") -> Bi-Fold Doors | D6: 45788 | E6: Commercial | F6: Tiruchirappalli | G6: Rahul | H6: Website | I6: P006 | J6: Bi-Fold Doors | K6: Doors | L6: 1 | M6: 59423 | N6: 0.05 | O6: 59423 | P6: 2971.15 | Q6: 56451.85 | R6: =YEAR(Sales_Data[[#This Row],[Order_Date]]) -> 2025 | S6: =TEXT(Sales_Data[[#This Row],[Order_Date]],"mmmm") -> May | T6: =MONTH($D6) -> 5 | U6: ="Q"&ROUNDUP(MONTH(Sales_Data[[#This Row],[Order_Date]])/3,0) -> Q2 | V6: Site Visit | W6: Paid | X6: Completed | Y6: 3 | Z6: 11 | AA6: 4 | AB6: May | AC6: Q2 | AD6: 2025
A7: FN10010 | B7: CUST1010 | C7: =_xlfn.XLOOKUP(Sales_Data[[#This Row],[Product_ID]],Product_Master[Product_ID],Product_Master[Product],"Not Found") -> Casement Windows | D7: 45753 | E7: Residential | F7: Tiruchirappalli | G7: Rahul | H7: Walk-in | I7: P005 | J7: Casement Windows | K7: Windows | L7: 4 | M7: 29299 | N7: 0.05 | O7: 117196 | P7: 5859.8 | Q7: 111336.2 | R7: =YEAR(Sales_Data[[#This Row],[Order_Date]]) -> 2025 | S7: =TEXT(Sales_Data[[#This Row],[Order_Date]],"mmmm") -> April | T7: =MONTH($D7) -> 4 | U7: ="Q"&ROUNDUP(MONTH(Sales_Data[[#This Row],[Order_Date]])/3,0) -> Q2 | V7: Converted | W7: Paid | X7: Completed | Y7: 6 | Z7: 6 | AA7: 5 | AB7: Apr | AC7: Q2 | AD7: 2025
A8: FN10011 | B8: CUST1011 | C8: =_xlfn.XLOOKUP(Sales_Data[[#This Row],[Product_ID]],Product_Master[Product_ID],Product_Master[Product],"Not Found") -> Bi-Fold Doors | D8: 45791 | E8: Commercial | F8: Madurai | G8: Rahul | H8: Google Ads | I8: P006 | J8: Bi-Fold Doors | K8: Doors | L8: 4 | M8: 60550 | N8: 0.05 | O8: 242200 | P8: 12110 | Q8: 230090 | R8: =YEAR(Sales_Data[[#This Row],[Order_Date]]) -> 2025 | S8: =TEXT(Sales_Data[[#This Row],[Order_Date]],"mmmm") -> May | T8: =MONTH($D8) -> 5 | U8: ="Q"&ROUNDUP(MONTH(Sales_Data[[#This Row],[Order_Date]])/3,0) -> Q2 | V8: Converted | W8: Paid | X8: Scheduled | Y8: 1 | Z8: 29 | AA8: 5 | AB8: May | AC8: Q2 | AD8: 2025
A9: FN10014 | B9: CUST1014 | C9: =_xlfn.XLOOKUP(Sales_Data[[#This Row],[Product_ID]],Product_Master[Product_ID],Product_Master[Product],"Not Found") -> French Doors | D9: 45711 | E9: Commercial | F9: Coimbatore | G9: Vikram | H9: Referral | I9: P004 | J9: French Doors | K9: Doors | L9: 5 | M9: 41423 | N9: 0.1 | O9: 207115 | P9: 20711.5 | Q9: 186403.5 | R9: =YEAR(Sales_Data[[#This Row],[Order_Date]]) -> 2025 | S9: =TEXT(Sales_Data[[#This Row],[Order_Date]],"mmmm") -> February | T9: =MONTH($D9) -> 2 | U9: ="Q"&ROUNDUP(MONTH(Sales_Data[[#This Row],[Order_Date]])/3,0) -> Q1 | V9: Converted | W9: Paid | X9: In Progress | Y9: 7 | Z9: 15 | AA9: 4 | AB9: Feb | AC9: Q1 | AD9: 2025
A10: FN10015 | B10: CUST1015 | C10: =_xlfn.XLOOKUP(Sales_Data[[#This Row],[Product_ID]],Product_Master[Product_ID],Product_Master[Product],"Not Found") -> uPVC Windows | D10: 45912 | E10: Commercial | F10: Madurai | G10: Rahul | H10: Instagram | I10: P001 | J10: uPVC Windows | K10: Windows | L10: 6 | M10: 17855 | N10: 0.1 | O10: 107130 | P10: 10713 | Q10: 96417 | R10: =YEAR(Sales_Data[[#This Row],[Order_Date]]) -> 2025 | S10: =TEXT(Sales_Data[[#This Row],[Order_Date]],"mmmm") -> September | T10: =MONTH($D10) -> 9 | U10: ="Q"&ROUNDUP(MONTH(Sales_Data[[#This Row],[Order_Date]])/3,0) -> Q3 | V10: Converted | W10: Pending | X10: Completed | Y10: 6 | Z10: 20 | AA10: 2 | AB10: Sep | AC10: Q3 | AD10: 2025
A11: FN10017 | B11: CUST1017 | C11: =_xlfn.XLOOKUP(Sales_Data[[#This Row],[Product_ID]],Product_Master[Product_ID],Product_Master[Product],"Not Found") -> French Doors | D11: 45808 | E11: Commercial | F11: Coimbatore | G11: Meena | H11: Website | I11: P004 | J11: French Doors | K11: Doors | L11: 6 | M11: 45105 | N11: 0.05 | O11: 270630 | P11: 13531.5 | Q11: 257098.5 | R11: =YEAR(Sales_Data[[#This Row],[Order_Date]]) -> 2025 | S11: =TEXT(Sales_Data[[#This Row],[Order_Date]],"mmmm") -> May | T11: =MONTH($D11) -> 5 | U11: ="Q"&ROUNDUP(MONTH(Sales_Data[[#This Row],[Order_Date]])/3,0) -> Q2 | V11: Negotiation | W11: Paid | X11: Delayed | Y11: 6 | Z11: 16 | AA11: 4 | AB11: May | AC11: Q2 | AD11: 2025
A12: FN10020 | B12: CUST1020 | C12: =_xlfn.XLOOKUP(Sales_Data[[#This Row],[Product_ID]],Product_Master[Product_ID],Product_Master[Product],"Not Found") -> Bi-Fold Doors | D12: 45934 | E12: Residential | F12: Chennai | G12: Meena | H12: Website | I12: P006 | J12: Bi-Fold Doors | K12: Doors | L12: 4 | M12: 54538 | N12: 0.15 | O12: 218152 | P12: 32722.8 | Q12: 185429.2 | R12: =YEAR(Sales_Data[[#This Row],[Order_Date]]) -> 2025 | S12: =TEXT(Sales_Data[[#This Row],[Order_Date]],"mmmm") -> October | T12: =MONTH($D12) -> 10 | U12: ="Q"&ROUNDUP(MONTH(Sales_Data[[#This Row],[Order_Date]])/3,0) -> Q4 | V12: Negotiation | W12: Paid | X12: In Progress | Y12: 6 | Z12: 18 | AA12: 4 | AB12: Oct | AC12: Q4 | AD12: 2025
A13: FN10024 | B13: CUST1024 | C13: =_xlfn.XLOOKUP(Sales_Data[[#This Row],[Product_ID]],Product_Master[Product_ID],Product_Master[Product],"Not Found") -> Soundproof Windows | D13: 45831 | E13: Commercial | F13: Tiruchirappalli | G13: Rahul | H13: Google Ads | I13: P008 | J13: Soundproof Windows | K13: Windows | L13: 2 | M13: 50580 | N13: 0.2 | O13: 101160 | P13: 20232 | Q13: 80928 | R13: =YEAR(Sales_Data[[#This Row],[Order_Date]]) -> 2025 | S13: =TEXT(Sales_Data[[#This Row],[Order_Date]],"mmmm") -> June | T13: =MONTH($D13) -> 6 | U13: ="Q"&ROUNDUP(MONTH(Sales_Data[[#This Row],[Order_Date]])/3,0) -> Q2 | V13: New | W13: Partially Paid | X13: In Progress | Y13: 3 | Z13: 26 | AA13: 4 | AB13: Jun | AC13: Q2 | AD13: 2025
... A422: FN10800 | B422: CUST1800 | C422: =_xlfn.XLOOKUP(Sales_Data[[#This Row],[Product_ID]],Product_Master[Product_ID],Product_Master[Product],"Not Found") -> Casement Windows | D422: 45991 | E422: Residential | F422: Madurai | G422: Karthik | H422: Referral | I422: P005 | J422: Casement Windows | K422: Windows | L422: 1 | M422: 29465 | N422: 0.2 | O422: 29465 | P422: 5893 | Q422: 23572 | R422: =YEAR(Sales_Data[[#This Row],[Order_Date]]) -> 2025 | S422: =TEXT(Sales_Data[[#This Row],[Order_Date]],"mmmm") -> November | T422: =MONTH($D422) -> 11 | U422: ="Q"&ROUNDUP(MONTH(Sales_Data[[#This Row],[Order_Date]])/3,0) -> Q4 | V422: Site Visit | W422: Partially Paid | X422: In Progress | Y422: 7 | Z422: 8 | AA422: 2 | AB422: Nov | AC422: Q4 | AD422: 2025

Sheet Product_Master
A1: Product_ID | B1: Product | C1: Category | D1: Standard_Price | E1: Warranty_Years | F1: Sales_Representative
A2: P001 | B2: uPVC Windows | C2: Windows | D2: 18000 | E2: 10 | F2: Arun
A3: P002 | B3: Aluminium Windows | C3: Windows | D3: 22000 | E3: 10 | F3: Priya
A4: P003 | B4: Sliding Doors | C4: Doors | D4: 35000 | E4: 5 | F4: Rahul
A5: P004 | B5: French Doors | C5: Doors | D5: 42000 | E5: 5 | F5: Sneha
A6: P005 | B6: Casement Windows | C6: Windows | D6: 26000 | E6: 10 | F6: Vikram
A7: P006 | B7: Bi-Fold Doors | C7: Doors | D7: 55000 | E7: 5 | F7: Divya
A8: P007 | B8: uPVC Doors | C8: Doors | D8: 30000 | E8: 5 | F8: Karthik
A9: P008 | B9: Soundproof Windows | C9: Windows | D9: 48000 | E9: 10 | F9: Meena
A12: Product_id | B12: P005
A13: Standard_Price | B13: =INDEX(Product_Master!$A$2:$F$9,MATCH(B12,Product_Master!$A$2:$A$9,0),MATCH(A13,Product_Master!$A$1:$F$1,0)) -> 26000 | C13: =_xlfn.FORMULATEXT(B13) -> =INDEX(Product_Master!$A$2:$F$9,MATCH(B12,Product_Master!$A$2:$A$9,0),MATCH(A13,Product_Master!$A$1:$F$1,0))
B14: =INDEX(Product_Master[],MATCH(B12,Product_Master[Product_ID],0),MATCH(A13,Product_Master[#Headers],0)) -> 26000 | C14: =_xlfn.FORMULATEXT(B14) -> =INDEX(Product_Master,MATCH(B12,Product_Master[Product_ID],0),MATCH(A13,Product_Master[#Headers],0))

Sheet vlookup+match
A1: VLOOKUP + MATCH
A3: A | B3: B
A4: Product ID | B4: P005
A5: Information Required | B5: Standard_Price | C5: =VLOOKUP(lookup_value, table_array, col_index_num, [range_lookup])
A6: Result | B6: ? | C6: =MATCH(lookup_value, lookup_array, [match_type])
C7: =HLOOKUP(lookup_value, table_array, row_index_num, [range_lookup])
B9: =VLOOKUP(B4,Product_Master[#All],4,0) -> 26000 | C9: =_xlfn.FORMULATEXT(B9) -> =VLOOKUP(B4,Product_Master[#All],4,0)
B10: =VLOOKUP(B4,Product_Master[],4,0) -> 26000 | C10: =_xlfn.FORMULATEXT(B10) -> =VLOOKUP(B4,Product_Master,4,0)
B11: =VLOOKUP(B4,Product_Master[#All],MATCH(B5,Product_Master[#Headers],0),FALSE) -> 26000 | C11: =_xlfn.FORMULATEXT(B11) -> =VLOOKUP(B4,Product_Master[#All],MATCH(B5,Product_Master[#Headers],0),FALSE)

Sheet Employee_Master
A1: Employee_ID | B1: Salesperson | C1: Team | D1: Designation | E1: Experience_Years | F1: District
A2: EMP001 | B2: Arun | C2: Retail | D2: Sales Executive | E2: 4 | F2: Chennai
A3: EMP002 | B3: Priya | C3: Retail | D3: Senior Sales Executive | E3: 6 | F3: Coimbatore
A4: EMP006 | B4: Divya | C4: Retail | D4: Sales Executive | E4: 3 | F4: Madurai
A5: EMP007 | B5: Karthik | C5: Projects | D5: Sales Manager | E5: 6 | F5: Tiruchirappalli

Sheet District_Master
A1: District_ID | B1: District | C1: State | D1: Region | E1: Branch_Manager | F1: Monthly_Target
A2: D001 | B2: Chennai | C2: Tamil Nadu | D2: South | E2: Suresh | F2: 3500000
A3: D002 | B3: Coimbatore | C3: Tamil Nadu | D3: South | E3: Lakshmi | F3: 2200000
A4: D006 | B4: Madurai | C4: Tamil Nadu | D4: South | E4: Bala | F4: 1500000
A5: D007 | B5: Tiruchirappalli | C5: Tamil Nadu | D5: South | E5: Naveen | F5: 1200000

Sheet Monthly_Target
A1: Months | B1: Jan | C1: Feb | D1: Mar | E1: Apr | F1: May | G1: Jun | H1: Jul | I1: Aug | J1: Sep | K1: Oct | L1: Nov | M1: Dec
A2: Sales Target | B2: 3200000 | C2: 3000000 | D2: 3400000 | E2: 3600000 | F2: 3700000 | G2: 3500000 | H2: 3800000 | I2: 3900000 | J2: 4000000 | K2: 4200000 | L2: 4400000 | M2: 4600000
A5: Months | B5: Aug
A6: Sales target | B6: =INDEX(Monthly_Target!$A$1:$M$2,MATCH(A6,Monthly_Target!$A$1:$A$2,0),MATCH(B5,Monthly_Target!$A$1:$M$1,0)) -> 3900000 | C6: =_xlfn.FORMULATEXT(B6) -> =INDEX(Monthly_Target!$A$1:$M$2,MATCH(A6,Monthly_Target!$A$1:$A$2,0),MATCH(B5,Monthly_Target!$A$1:$M$1,0))
B7: =INDEX($A$1:$M$2,MATCH(A6,A1:A2,0),MATCH(B5,A1:M1,0)) -> 3900000 | C7: =_xlfn.FORMULATEXT(B7) -> =INDEX($A$1:$M$2,MATCH(A6,A1:A2,0),MATCH(B5,A1:M1,0))

Sheet Hlookup+match
E6: =MATCH(lookup_value, lookup_array, match_type)
E7: =HLOOKUP(lookup_value, table_array, row_index_num, [range_lookup])
A8: A | B8: B
A9: Enter Month | B9: aug | D9: =HLOOKUP(B9,Monthly_Target[#All],MATCH(A10,Monthly_Target[],0)+1,FALSE) -> 3900000 | E9: =_xlfn.FORMULATEXT(D9) -> =HLOOKUP(B9,Monthly_Target[#All],MATCH(A10,Monthly_Target,0)+1,FALSE)
A10: Sales Target | B10: ? | D10: =HLOOKUP(B9,Monthly_Target[#All],2,0) -> 3900000 | E10: =_xlfn.FORMULATEXT(D10) -> =HLOOKUP(B9,Monthly_Target[#All],2,0)
D13: =INDEX(Monthly_Target[#All],MATCH(A10,Monthly_Target!A1:A2,0),MATCH(B9,Monthly_Target!A1:M1,0)) -> 3900000 | E13: =_xlfn.FORMULATEXT(D13) -> =INDEX(Monthly_Target[#All],MATCH(A10,Monthly_Target!A1:A2,0),MATCH(B9,Monthly_Target!A1:M1,0))

Sheet index+match
A1: A | B1: B
A2: Product ID | B2: P005
A3: Information Required | B3: Standard_Price | F3: =INDEX(array, row_num, [column_num]
A4: Result | B4: =INDEX(Product_Master!$A$2:$F$9,MATCH(B2,Product_Master!$A$2:$A$9,0),MATCH(B3,Product_Master!$A$1:$F$1,0)) -> 26000 | C4: =_xlfn.FORMULATEXT(B4) -> =INDEX(Product_Master!$A$2:$F$9,MATCH(B2,Product_Master!$A$2:$A$9,0),MATCH(B3,Product_Master!$A$1:$F$1,0))
